assetbot/__init__.py
assetbot/assetbot.py
assetbot/config.py
assetbot/example_config.toml
assetbot/exporters/__init__.py
assetbot/exporters/base.py
assetbot/exporters/copy.py
assetbot/exporters/gimp.py
assetbot/exporters/krita.py
assetbot/exporters/svg.py
assetbot-0.1.2.dist-info/METADATA
assetbot-0.1.2.dist-info/WHEEL
assetbot-0.1.2.dist-info/entry_points.txt
assetbot-0.1.2.dist-info/licenses/COPYING
assetbot-0.1.2.dist-info/RECORD
