Metadata-Version: 2.3
Name: assetbot
Version: 0.1.2
Summary: A generalized, extensible hot reloader tool in Python
Project-URL: Homepage, https://github.com/aghorui/assetbot
Project-URL: Issues, https://github.com/aghorui/assetbot/issues
Author-email: aghorui <aghorui.software@gmail.com>
License-File: COPYING
Classifier: License :: OSI Approved :: BSD License
Classifier: Operating System :: OS Independent
Classifier: Programming Language :: Python :: 3
Requires-Python: >=3.10.12
Requires-Dist: toml>=0.10.2
Requires-Dist: watchdog>=4.0.0
